<?xml version="1.0" encoding="utf-8" ?>
<dwsync>
<file name="about.jpg" server="192.168.1.25//var/www/html/" local="132919095018203048" remote="132965788100000000" Dst="2" />
<file name="apple-touch-icon.png" server="192.168.1.25//var/www/html/" local="132982344290959068" remote="132982345570000000" Dst="2" />
<file name="favicon.png" server="192.168.1.25//var/www/html/" local="132918609794365205" remote="132965788100000000" Dst="2" />
<file name="footer-bg.jpg" server="192.168.1.25//var/www/html/" local="132982348318817501" remote="132982366410000000" Dst="2" />
<file name="logo.png" server="192.168.1.25//var/www/html/" local="132918643286401467" remote="132965788100000000" Dst="2" />
<file name="mn-logo.png" server="192.168.1.25//var/www/html/" local="132918635074733464" remote="132965788100000000" Dst="2" />
<file name="mn-logo_WIT.png" server="192.168.1.25//var/www/html/" local="132918562155227445" remote="132965788100000000" Dst="2" />
<file name="testimonials-bg.jpg" server="192.168.1.25//var/www/html/" local="132982358041213531" remote="132982359080000000" Dst="2" />
</dwsync>